pyfis/__init__.py
pyfis/metadata.py
pyfis/aegmis/__init__.py
pyfis/aegmis/ecs_lcd.py
pyfis/aegmis/exceptions.py
pyfis/aegmis/mis1_board.py
pyfis/aegmis/mis1_matrix.py
pyfis/aegmis/mis1_protocol.py
pyfis/aegmis/mis1_text.py
pyfis/aegmis/mis2_protocol.py
pyfis/aegmis/mis2_text.py
pyfis/aesys/__init__.py
pyfis/aesys/dsa.py
pyfis/data_sources/__init__.py
pyfis/data_sources/fraport.py
pyfis/gpio_backends/__init__.py
pyfis/gpio_backends/rpi_gpio.py
pyfis/ibis/__init__.py
pyfis/ibis/ibis_protocol.py
pyfis/ibis/ibis_serial.py
pyfis/ibis/ibis_tcp.py
pyfis/krone/__init__.py
pyfis/krone/exceptions.py
pyfis/krone/k8200.py
pyfis/krone/k8200_pst.py
pyfis/krone/k9000_fbk.py
pyfis/krone/k9000_fbm.py
pyfis/krone/k9000_hlst.py
pyfis/krone/k9000_rs485.py
pyfis/krone/util.py
pyfis/lawo/__init__.py
pyfis/lawo/lawo_font.py
pyfis/lawo/mono_protocol.py
pyfis/lawo/mono_serial.py
pyfis/microsyst/__init__.py
pyfis/microsyst/migra.py
pyfis/mobitec/__init__.py
pyfis/mobitec/matrix.py
pyfis/oltmann/__init__.py
pyfis/oltmann/dimensions-10.json
pyfis/oltmann/dimensions-11.json
pyfis/oltmann/dimensions-12.json
pyfis/oltmann/dimensions-14.json
pyfis/oltmann/dimensions-16.json
pyfis/oltmann/dimensions-240.json
pyfis/oltmann/dimensions-4.json
pyfis/oltmann/dimensions-5.json
pyfis/oltmann/dimensions-76.json
pyfis/oltmann/dimensions-77.json
pyfis/oltmann/dimensions-8.json
pyfis/oltmann/dimensions-9.json
pyfis/oltmann/utils.py
pyfis/oltmann/vistra_i.py
pyfis/omega/__init__.py
pyfis/omega/rs485.py
pyfis/splitflap_display/__init__.py
pyfis/splitflap_display/ascii_graphics.py
pyfis/splitflap_display/display.py
pyfis/splitflap_display/fields.py
pyfis/splitflap_display/gui.py
pyfis/utils/__init__.py
pyfis/utils/base_serial.py
pyfis/utils/dummy_serial.py
pyfis/utils/tcp_serial.py
pyfis/utils/utils.py
pyfis/xatlabs/__init__.py
pyfis/xatlabs/cheetah.py
pyfis/xatlabs/exceptions.py
pyfis/xatlabs/rgb_dsa.py
pyfis/xatlabs/splitflap.py
pyfis-1.14.2.dist-info/licenses/LICENSE
pyfis-1.14.2.dist-info/METADATA
pyfis-1.14.2.dist-info/WHEEL
pyfis-1.14.2.dist-info/top_level.txt
pyfis-1.14.2.dist-info/RECORD
